security_scanner_analyzers/__init__.py
security_scanner_analyzers/utils.py
security_scanner_analyzers/cloudsploit/__init__.py
security_scanner_analyzers/cloudsploit/__main__.py
security_scanner_analyzers/cloudsploit/parser.py
security_scanner_analyzers/nuclei/__init__.py
security_scanner_analyzers/nuclei/__main__.py
security_scanner_analyzers/nuclei/nuclei.py
security_scanner_analyzers-0.4.1.dist-info/licenses/LICENSE
security_scanner_analyzers-0.4.1.dist-info/METADATA
security_scanner_analyzers-0.4.1.dist-info/WHEEL
security_scanner_analyzers-0.4.1.dist-info/top_level.txt
security_scanner_analyzers-0.4.1.dist-info/RECORD
