Metadata-Version: 2.4
Name: security-scanner-analyzers
Version: 0.4.1
Summary: A collection of security scanner analyzers
Requires-Python: >=3.10
License-File: LICENSE
Requires-Dist: requests>=2.32.5
Dynamic: license-file
